[
  {
    "endTime" : "2023-12-05 05:33",
    "podcastName" : "Koya sleep music",
    "episodeName" : "music for sleep koya",
    "msPlayed" : 21777
  },
  {
    "endTime" : "2023-12-05 05:33",
    "podcastName" : "Koya sleep music",
    "episodeName" : "music for sleep koya",
    "msPlayed" : 3600195
  },
  {
    "endTime" : "2023-12-06 05:08",
    "podcastName" : "Koya sleep music",
    "episodeName" : "music for sleep koya",
    "msPlayed" : 3583764
  },
  {
    "endTime" : "2023-12-06 05:18",
    "podcastName" : "Koya sleep music",
    "episodeName" : "music for sleep koya",
    "msPlayed" : 25255
  },
  {
    "endTime" : "2023-12-07 17:54",
    "podcastName" : "YT",
    "episodeName" : "DDAENG (땡)",
    "msPlayed" : 121690
  },
  {
    "endTime" : "2023-12-07 17:55",
    "podcastName" : "Radio Ambulante",
    "episodeName" : "El misterio de los fósiles",
    "msPlayed" : 0
  },
  {
    "endTime" : "2023-12-11 02:04",
    "podcastName" : "YT",
    "episodeName" : "DDAENG (땡)",
    "msPlayed" : 115964
  },
  {
    "endTime" : "2023-12-12 19:10",
    "podcastName" : "YT",
    "episodeName" : "DDAENG (땡)",
    "msPlayed" : 236964
  },
  {
    "endTime" : "2023-12-12 19:12",
    "podcastName" : "Una vida a tu medida",
    "episodeName" : "#53: De diseñador web a cerdo estratega — Arturo García",
    "msPlayed" : 84855
  },
  {
    "endTime" : "2023-12-13 23:32",
    "podcastName" : "YT",
    "episodeName" : "DDAENG (땡)",
    "msPlayed" : 236964
  },
  {
    "endTime" : "2023-12-14 23:38",
    "podcastName" : "YT",
    "episodeName" : "DDAENG (땡)",
    "msPlayed" : 236964
  },
  {
    "endTime" : "2024-01-16 00:54",
    "podcastName" : "YT",
    "episodeName" : "DDAENG (땡)",
    "msPlayed" : 236964
  },
  {
    "endTime" : "2024-01-17 23:34",
    "podcastName" : "YT",
    "episodeName" : "DDAENG (땡)",
    "msPlayed" : 236964
  },
  {
    "endTime" : "2024-02-01 00:18",
    "podcastName" : "YT",
    "episodeName" : "DDAENG (땡)",
    "msPlayed" : 236964
  },
  {
    "endTime" : "2024-02-15 03:55",
    "podcastName" : "Koya sleep music",
    "episodeName" : "music for sleep koya",
    "msPlayed" : 3581440
  },
  {
    "endTime" : "2024-02-15 04:05",
    "podcastName" : "Koya sleep music",
    "episodeName" : "music for sleep koya",
    "msPlayed" : 27740
  },
  {
    "endTime" : "2024-03-01 02:31",
    "podcastName" : "YT",
    "episodeName" : "DDAENG (땡)",
    "msPlayed" : 236964
  },
  {
    "endTime" : "2024-03-05 14:33",
    "podcastName" : "YT",
    "episodeName" : "DDAENG (땡)",
    "msPlayed" : 9830
  },
  {
    "endTime" : "2024-03-12 00:00",
    "podcastName" : "YT",
    "episodeName" : "DDAENG (땡)",
    "msPlayed" : 227964
  },
  {
    "endTime" : "2024-03-18 20:09",
    "podcastName" : "YT",
    "episodeName" : "DDAENG (땡)",
    "msPlayed" : 1300
  },
  {
    "endTime" : "2024-04-02 00:04",
    "podcastName" : "YT",
    "episodeName" : "DDAENG (땡)",
    "msPlayed" : 14191
  },
  {
    "endTime" : "2024-04-09 00:22",
    "podcastName" : "YT",
    "episodeName" : "DDAENG (땡)",
    "msPlayed" : 177037
  },
  {
    "endTime" : "2024-04-24 05:19",
    "podcastName" : "Koya sleep music",
    "episodeName" : "music for sleep koya",
    "msPlayed" : 23771
  },
  {
    "endTime" : "2024-04-24 05:19",
    "podcastName" : "Koya sleep music",
    "episodeName" : "music for sleep koya",
    "msPlayed" : 3579088
  },
  {
    "endTime" : "2024-04-24 05:29",
    "podcastName" : "Koya sleep music",
    "episodeName" : "music for sleep koya",
    "msPlayed" : 12179
  },
  {
    "endTime" : "2024-04-24 13:15",
    "podcastName" : "YT",
    "episodeName" : "DDAENG (땡)",
    "msPlayed" : 236964
  },
  {
    "endTime" : "2024-05-09 00:39",
    "podcastName" : "YT",
    "episodeName" : "DDAENG (땡)",
    "msPlayed" : 17358
  },
  {
    "endTime" : "2024-06-01 02:02",
    "podcastName" : "Thinking in English",
    "episodeName" : "298. Wealth and Inequality: Should Inheritance Be Abolished? (English Vocabulary Lesson)",
    "msPlayed" : 31258
  },
  {
    "endTime" : "2024-06-01 02:10",
    "podcastName" : "Thinking in English",
    "episodeName" : "296. What is Happening in Haiti? (English Vocabulary Lesson)",
    "msPlayed" : 516426
  },
  {
    "endTime" : "2024-06-01 02:11",
    "podcastName" : "Leyendas Legendarias",
    "episodeName" : "E274: Fugas de Prisión: De Alcatraz a Australia",
    "msPlayed" : 5640
  },
  {
    "endTime" : "2024-06-01 02:12",
    "podcastName" : "Serialmente | PIA Podcast",
    "episodeName" : "Serialmente: Final de Temporada | Asesinos Seriales Que Nunca Fueron",
    "msPlayed" : 21520
  },
  {
    "endTime" : "2024-06-01 02:25",
    "podcastName" : "TED Talks Daily",
    "episodeName" : "The problem with being \"too nice\" at work | Tessa West",
    "msPlayed" : 184280
  },
  {
    "endTime" : "2024-06-28 01:35",
    "podcastName" : "Aleja y La Grúa PODCAST",
    "episodeName" : "EP191 Profesiones | Show en Vivo Barranquilla | Y la VaJJ consultando",
    "msPlayed" : 32
  },
  {
    "endTime" : "2024-06-28 01:35",
    "podcastName" : "Aleja y La Grúa PODCAST",
    "episodeName" : "EP191 Profesiones | Show en Vivo Barranquilla | Y la VaJJ consultando",
    "msPlayed" : 1506
  },
  {
    "endTime" : "2024-06-28 01:35",
    "podcastName" : "Aleja y La Grúa PODCAST",
    "episodeName" : "EP191 Profesiones | Show en Vivo Barranquilla | Y la VaJJ consultando",
    "msPlayed" : 2518
  },
  {
    "endTime" : "2024-06-28 13:28",
    "podcastName" : "Aleja y La Grúa PODCAST",
    "episodeName" : "EP191 Profesiones | Show en Vivo Barranquilla | Y la VaJJ consultando",
    "msPlayed" : 7218
  },
  {
    "endTime" : "2024-06-28 13:28",
    "podcastName" : "Aleja y La Grúa PODCAST",
    "episodeName" : "EP191 Profesiones | Show en Vivo Barranquilla | Y la VaJJ consultando",
    "msPlayed" : 0
  },
  {
    "endTime" : "2024-07-24 14:43",
    "podcastName" : "Tatan y Maleja ",
    "episodeName" : "Ep 1 - Vamos a incomodarnos",
    "msPlayed" : 0
  },
  {
    "endTime" : "2024-07-24 14:43",
    "podcastName" : "Tatan y Maleja ",
    "episodeName" : "Ep 1 - Vamos a incomodarnos",
    "msPlayed" : 15250
  },
  {
    "endTime" : "2024-07-24 14:50",
    "podcastName" : "Tatan y Maleja ",
    "episodeName" : "Ep 1 - Vamos a incomodarnos",
    "msPlayed" : 59982
  },
  {
    "endTime" : "2024-08-11 03:20",
    "podcastName" : "Tatan y Maleja ",
    "episodeName" : "Ep 3 - ¿Por qué te incomoda pedir ayuda?",
    "msPlayed" : 13453
  },
  {
    "endTime" : "2024-08-11 03:20",
    "podcastName" : "Tatan y Maleja ",
    "episodeName" : "Ep 3 - ¿Por qué te incomoda pedir ayuda?",
    "msPlayed" : 2917
  },
  {
    "endTime" : "2024-08-11 17:25",
    "podcastName" : "Tatan y Maleja ",
    "episodeName" : "Ep 3 - ¿Por qué te incomoda pedir ayuda?",
    "msPlayed" : 54
  },
  {
    "endTime" : "2024-08-12 00:39",
    "podcastName" : "Tatan y Maleja ",
    "episodeName" : "Ep 3 - ¿Por qué te incomoda pedir ayuda?",
    "msPlayed" : 32
  },
  {
    "endTime" : "2024-08-12 04:02",
    "podcastName" : "Tatan y Maleja ",
    "episodeName" : "Ep 3 - ¿Por qué te incomoda pedir ayuda?",
    "msPlayed" : 1962
  },
  {
    "endTime" : "2024-08-12 12:49",
    "podcastName" : "Tatan y Maleja ",
    "episodeName" : "Ep 3 - ¿Por qué te incomoda pedir ayuda?",
    "msPlayed" : 4944
  },
  {
    "endTime" : "2024-08-13 16:02",
    "podcastName" : "Tatan y Maleja ",
    "episodeName" : "Ep 3 - ¿Por qué te incomoda pedir ayuda?",
    "msPlayed" : 531
  },
  {
    "endTime" : "2024-08-22 01:22",
    "podcastName" : "Relatos Forenses Podcast",
    "episodeName" : "Ep. 47 Trabajo persiguiendo criminales \"Soy Reportera\" Paulina Marín l Relatos Forenses",
    "msPlayed" : 1936
  },
  {
    "endTime" : "2024-08-22 01:23",
    "podcastName" : "Relatos Forenses Podcast",
    "episodeName" : "Ep. 47 Trabajo persiguiendo criminales \"Soy Reportera\" Paulina Marín l Relatos Forenses",
    "msPlayed" : 59983
  },
  {
    "endTime" : "2024-08-24 13:58",
    "podcastName" : "Tatan y Maleja ",
    "episodeName" : "EP 6 - Sexo sin incomodidades",
    "msPlayed" : 0
  },
  {
    "endTime" : "2024-08-24 23:01",
    "podcastName" : "Tatan y Maleja ",
    "episodeName" : "EP 6 - Sexo sin incomodidades",
    "msPlayed" : 59991
  },
  {
    "endTime" : "2024-08-24 23:19",
    "podcastName" : "Tatan y Maleja ",
    "episodeName" : "EP 6 - Sexo sin incomodidades",
    "msPlayed" : 7379
  },
  {
    "endTime" : "2024-09-14 02:52",
    "podcastName" : "Classic Audiobook Collection",
    "episodeName" : "Pride and Prejudice by Jane Austen ~ Full Audiobook",
    "msPlayed" : 55560
  },
  {
    "endTime" : "2024-10-11 02:03",
    "podcastName" : "La Crónica Oscura",
    "episodeName" : "¿Monstruos? La historia real de Lyle y Erik Menéndez",
    "msPlayed" : 16317
  },
  {
    "endTime" : "2024-10-11 02:08",
    "podcastName" : "La Crónica Oscura",
    "episodeName" : "¿Monstruos? La historia real de Lyle y Erik Menéndez",
    "msPlayed" : 0
  },
  {
    "endTime" : "2024-10-11 02:08",
    "podcastName" : "La Crónica Oscura",
    "episodeName" : "¿Monstruos? La historia real de Lyle y Erik Menéndez",
    "msPlayed" : 268
  },
  {
    "endTime" : "2024-10-11 14:24",
    "podcastName" : "La Crónica Oscura",
    "episodeName" : "¿Monstruos? La historia real de Lyle y Erik Menéndez",
    "msPlayed" : 9
  },
  {
    "endTime" : "2024-10-21 13:48",
    "podcastName" : "Tu amiga psicóloga",
    "episodeName" : "Construyendo una confianza en ti real: 6 tips para empezar.",
    "msPlayed" : 224
  },
  {
    "endTime" : "2024-10-21 17:09",
    "podcastName" : "Tu amiga psicóloga",
    "episodeName" : "Construyendo una confianza en ti real: 6 tips para empezar.",
    "msPlayed" : 28
  },
  {
    "endTime" : "2024-11-03 14:34",
    "podcastName" : "La cuarta es la vencida",
    "episodeName" : "100. Transforma la queja",
    "msPlayed" : 1184
  },
  {
    "endTime" : "2024-11-03 14:34",
    "podcastName" : "La cuarta es la vencida",
    "episodeName" : "100. Transforma la queja",
    "msPlayed" : 0
  },
  {
    "endTime" : "2024-11-03 16:30",
    "podcastName" : "La cuarta es la vencida",
    "episodeName" : "100. Transforma la queja",
    "msPlayed" : 355
  },
  {
    "endTime" : "2024-11-03 16:30",
    "podcastName" : "La cuarta es la vencida",
    "episodeName" : "100. Transforma la queja",
    "msPlayed" : 162
  },
  {
    "endTime" : "2024-11-03 17:32",
    "podcastName" : "La cuarta es la vencida",
    "episodeName" : "100. Transforma la queja",
    "msPlayed" : 517
  },
  {
    "endTime" : "2024-11-16 05:03",
    "podcastName" : "Just Sleep - Bedtime Stories for Adults",
    "episodeName" : "Pride and Prejudice Chapters 1-5 by Jane Austen",
    "msPlayed" : 123960
  },
  {
    "endTime" : "2024-11-16 05:09",
    "podcastName" : "Dormicast",
    "episodeName" : "Duerme sin ansiedad",
    "msPlayed" : 293246
  },
  {
    "endTime" : "2024-11-16 07:59",
    "podcastName" : "Podcast para dormirse",
    "episodeName" : "356. 💤 8 horas SIN CORTES de historias para dormir",
    "msPlayed" : 2694173
  },
  {
    "endTime" : "2024-11-17 04:13",
    "podcastName" : "Podcast para dormirse",
    "episodeName" : "💤 PARA DORMIRSE 380. 🐦 El seguidor del ave Fenix",
    "msPlayed" : 104231
  },
  {
    "endTime" : "2024-11-18 02:41",
    "podcastName" : "Gaby del Río, La voz del libro",
    "episodeName" : "El retrato de Dorian Gray - Oscar Wilde",
    "msPlayed" : 88607
  },
  {
    "endTime" : "2024-11-18 05:14",
    "podcastName" : "Salud Mental✨ con Alan Disavia",
    "episodeName" : "Hipnosis para dormir profundamente 🪄✨",
    "msPlayed" : 1373396
  }
]